{
	"configurations" : 
	[
		{
			"directories" : 
			[
				{
					"build" : ".",
					"jsonFile" : "directory-.-Debug-d0094a50bb2071803777.json",
					"minimumCMakeVersion" : 
					{
						"string" : "3.16"
					},
					"projectIndex" : 0,
					"source" : ".",
					"targetIndexes" : 
					[
						0,
						1,
						2
					]
				}
			],
			"name" : "Debug",
			"projects" : 
			[
				{
					"directoryIndexes" : 
					[
						0
					],
					"name" : "pricer-structured",
					"targetIndexes" : 
					[
						0,
						1,
						2
					]
				}
			],
			"targets" : 
			[
				{
					"directoryIndex" : 0,
					"id" : "pricer_gui::@6890427a1f51a3e7e1df",
					"jsonFile" : "target-pricer_gui-Debug-1548ee587dc7438f14bf.json",
					"name" : "pricer_gui",
					"projectIndex" : 0
				},
				{
					"directoryIndex" : 0,
					"id" : "pricer_gui_autogen::@6890427a1f51a3e7e1df",
					"jsonFile" : "target-pricer_gui_autogen-Debug-f16f0eea27eb7414126b.json",
					"name" : "pricer_gui_autogen",
					"projectIndex" : 0
				},
				{
					"directoryIndex" : 0,
					"id" : "pricer_gui_autogen_timestamp_deps::@6890427a1f51a3e7e1df",
					"jsonFile" : "target-pricer_gui_autogen_timestamp_deps-Debug-d749bfb37696131db601.json",
					"name" : "pricer_gui_autogen_timestamp_deps",
					"projectIndex" : 0
				}
			]
		}
	],
	"kind" : "codemodel",
	"paths" : 
	{
		"build" : "C:/Users/bagot/OneDrive/Documents/GitHub/pricer-structured/build/Desktop_Qt_6_10_1_MinGW_64_bit-Debug",
		"source" : "C:/Users/bagot/OneDrive/Documents/GitHub/pricer-structured"
	},
	"version" : 
	{
		"major" : 2,
		"minor" : 7
	}
}
